ellipsis/__init__.py
ellipsis/_listener.py
ellipsis/cli.py
ellipsis/ellipsis_api_client.py
ellipsis/src/__init__.py
ellipsis/src/listener/__init__.py
ellipsis/src/listener/cloud_dev_env_listener.py
ellipsis/src/models/__init__.py
ellipsis/src/models/workspaces/__init__.py
ellipsis/src/models/workspaces/command.py
ellipsis/src/models/workspaces/constants.py
ellipsis/src/models/workspaces/models.py
ellipsis_cli-0.2.7.dist-info/entry_points.txt
ellipsis_cli-0.2.7.dist-info/LICENSE
ellipsis_cli-0.2.7.dist-info/WHEEL
ellipsis_cli-0.2.7.dist-info/METADATA
ellipsis_cli-0.2.7.dist-info/RECORD
